podiff.py
setup.py
podiff.egg-info/PKG-INFO
podiff.egg-info/SOURCES.txt
podiff.egg-info/dependency_links.txt
podiff.egg-info/entry_points.txt
podiff.egg-info/requires.txt
podiff.egg-info/top_level.txt