Metadata-Version: 1.0
Name: podiff
Version: 0.1
Summary: Sematically compare two .po/gettext files for differences, ignoring, ordering, whitespace, comments, etc.
Home-page: UNKNOWN
Author: Rory McCann
Author-email: rory@technomancy.org
License: GPLv3
Platform: UNKNOWN
